mcp_weather_server/__init__.py
mcp_weather_server/__main__.py
mcp_weather_server/server.py
mcp_weather_server/utils.py
mcp_weather_server/tools/__init__.py
mcp_weather_server/tools/air_quality_service.py
mcp_weather_server/tools/toolhandler.py
mcp_weather_server/tools/tools_air_quality.py
mcp_weather_server/tools/tools_time.py
mcp_weather_server/tools/tools_weather.py
mcp_weather_server/tools/weather_service.py
mcp_weather_server-0.6.0.dist-info/licenses/LICENSE
mcp_weather_server-0.6.0.dist-info/METADATA
mcp_weather_server-0.6.0.dist-info/WHEEL
mcp_weather_server-0.6.0.dist-info/entry_points.txt
mcp_weather_server-0.6.0.dist-info/top_level.txt
mcp_weather_server-0.6.0.dist-info/RECORD
